matplotlib_cn_font/__init__.py
matplotlib_cn_font/matplotlib_cn_font.py
matplotlib_cn_font-0.0.0.dist-info/LICENSE
matplotlib_cn_font-0.0.0.dist-info/METADATA
matplotlib_cn_font-0.0.0.dist-info/WHEEL
matplotlib_cn_font-0.0.0.dist-info/top_level.txt
matplotlib_cn_font-0.0.0.dist-info/RECORD
