Metadata-Version: 2.1
Name: matplotlib-cn-font
Version: 0.0.0
Summary: A package to set Chinese font for matplotlib.
Home-page: https://github.com/Yanzhong-Hub/yzdb
Author: Yanzhong Huang
Author-email: yanzhong.huang@outlook.com
License: MIT
Classifier: Programming Language :: Python :: 3
Classifier: License :: OSI Approved :: MIT License
Requires-Python: >=3.5
License-File: LICENSE
Requires-Dist: matplotlib
Provides-Extra: dev
Requires-Dist: pytest (>=7.0) ; extra == 'dev'
Requires-Dist: twine (>=4.0.2) ; extra == 'dev'
